xterm/__init__.py
xterm/helpers.py
xterm/main.py
xterm/ext/__init__.py
xterm/ext/async.py
xterm/ext/games.py
xterm/ext/image.py
xterm_backup-0.7.3.dist-info/LICENCE
xterm_backup-0.7.3.dist-info/METADATA
xterm_backup-0.7.3.dist-info/WHEEL
xterm_backup-0.7.3.dist-info/top_level.txt
xterm_backup-0.7.3.dist-info/RECORD
