Metadata-Version: 2.1
Name: xterm-backup
Version: 0.7.3
Summary: Custom keyboard and mouse events for xterm_backup terminals
Home-page: https://repl.it/@mat1/Terminal-thing
Author: mat
Author-email: fake@email.lol
Classifier: Programming Language :: Python :: 3
Classifier: License :: OSI Approved :: MIT License
Classifier: Operating System :: OS Independent
License-File: LICENCE
Requires-Dist: Pillow
